brazilian_zipcode/__init__.py
brazilian_zipcode/api/__init__.py
brazilian_zipcode/api/serializers.py
brazilian_zipcode/api/urls.py
brazilian_zipcode/api/views.py
brazilian_zipcode/forms.py
brazilian_zipcode/injection.py
brazilian_zipcode/locale/pt_BR/LC_MESSAGES/django.po
brazilian_zipcode/objects.py
brazilian_zipcode/parsers/__init__.py
brazilian_zipcode/parsers/base.py
brazilian_zipcode/parsers/correios.py
brazilian_zipcode/service.py
brazilian_zipcode/static/getAddressInfo.js
brazilian_zipcode/urls.py
brazilian_zipcode/widgets.py
django_brazilian_zipcode-0.2.1.dist-info/WHEEL
django_brazilian_zipcode-0.2.1.dist-info/METADATA
django_brazilian_zipcode-0.2.1.dist-info/RECORD
