Metadata-Version: 2.1
Name: django-brazilian-zipcode
Version: 0.2.1
Summary: UNKNOWN
License: MIT
Author-email: Plathanus <leandrodesouzadev@gmail.com>
Requires-Python: >=3.8
Requires-Dist: django>=3.2,<4.0
Requires-Dist: djangorestframework>=3.13.1
Requires-Dist: requests>=2.27.1
Project-URL: Homepage, https://github.com/plathanus-tech/django-brazilian-zipcode
Project-URL: download_url, https://github.com/plathanus-tech/django-brazilian-zipcode/releases/tag/v0.2.1
